LICENSE
README.md
setup.py
novadata_utils/__init__.py
novadata_utils/apps.py
novadata_utils/urls.py
novadata_utils.egg-info/PKG-INFO
novadata_utils.egg-info/SOURCES.txt
novadata_utils.egg-info/dependency_links.txt
novadata_utils.egg-info/requires.txt
novadata_utils.egg-info/top_level.txt
novadata_utils/admin/__init__.py
novadata_utils/admin/novadata_model_admin.py
novadata_utils/auth/__init__.py
novadata_utils/auth/login_username_email.py
novadata_utils/breadcrumbs/__init__.py
novadata_utils/breadcrumbs/crud_breadcrumbs.py
novadata_utils/breadcrumbs/items.py
novadata_utils/breadcrumbs/make_breadcrumb.py
novadata_utils/breadcrumbs/make_item_breadcrumb.py
novadata_utils/forms/__init__.py
novadata_utils/forms/gerenciar_inline_form.py
novadata_utils/functions/__init__.py
novadata_utils/functions/get_prop.py
novadata_utils/functions/props_dict.py
novadata_utils/functions/transform_field.py
novadata_utils/managers/__init__.py
novadata_utils/middlewares/__init__.py
novadata_utils/migrations/0001_initial.py
novadata_utils/migrations/0002_alter_novadatamodel_usuario_criacao.py
novadata_utils/migrations/__init__.py
novadata_utils/models/__init__.py
novadata_utils/models/abstract_novadata_model.py
novadata_utils/models/novadata_model.py
novadata_utils/redirect/__init__.py
novadata_utils/redirect/reverse_lazy_plus.py
novadata_utils/save/__init__.py
novadata_utils/save/create_logs.py
novadata_utils/save/get_changes.py
novadata_utils/serializers/__init__.py
novadata_utils/serializers/novadata_model_serializer.py
novadata_utils/signals/__init__.py
novadata_utils/templatetags/__init__.py
novadata_utils/tests/__init__.py
novadata_utils/utils/__init__.py
novadata_utils/utils/camel_to_snake_case.py
novadata_utils/views/__init__.py
novadata_utils/views/base_site.py
novadata_utils/views/novadata_view.py
novadata_utils/viewsets/__init__.py
novadata_utils/viewsets/novadata_model_viewset.py
novadata_utils/viewsets/novadata_pagination.py