Metadata-Version: 2.1
Name: novadata_utils
Version: 0.4.2
Summary: novadata utils
Home-page: https://github.com/TimeNovaData/novadata_utils/
Author: Flávio Silva
Author-email: flavio.nogueira.profissional@gmail.com
License: MIT License
Project-URL: GitHub, https://github.com/TimeNovaData/novadata_utils/
Keywords: Django,utils,ndt,novadata,nova data,nova,data
License-File: LICENSE
Requires-Dist: django
Requires-Dist: djangorestframework
Requires-Dist: django-admin-list-filter-dropdown
Requires-Dist: django-admin-rangefilter
Requires-Dist: django-crum
Requires-Dist: django-import-export>=4.0.7
Requires-Dist: django-object-actions>=4.0.0
